x9k3/__init__.py
x9k3/abr.py
x9k3/argue.py
x9k3/scte35.py
x9k3/sliding.py
x9k3/x9k3.py
x9k3/x9mp.py
x9k3-1.0.13.data/scripts/adbreak3
x9k3-1.0.13.data/scripts/adinterval3
x9k3-1.0.13.data/scripts/x9k3
x9k3-1.0.13.dist-info/licenses/LICENSE
x9k3-1.0.13.dist-info/METADATA
x9k3-1.0.13.dist-info/WHEEL
x9k3-1.0.13.dist-info/top_level.txt
x9k3-1.0.13.dist-info/RECORD
