Metadata-Version: 2.4
Name: x9k3
Version: 1.0.13
Summary: ABR HLS Segmenter with SCTE-35 Injecton
Home-page: https://github.com/superkabuki/x9k3
Author: Adrian of Doom and a Cast of Thousands
Author-email: spam@iodisco.com
Platform: all
Classifier: License :: OSI Approved :: Sleepycat License
Classifier: Environment :: Console
Classifier: Operating System :: OS Independent
Classifier: Operating System :: POSIX :: BSD :: OpenBSD
Classifier: Operating System :: POSIX :: BSD :: NetBSD
Classifier: Operating System :: POSIX :: Linux
Classifier: Topic :: Multimedia :: Video
Classifier: Programming Language :: Python :: 3.9
Classifier: Programming Language :: Python :: Implementation :: PyPy
Classifier: Programming Language :: Python :: Implementation :: CPython
Requires-Python: >=3.9
License-File: LICENSE
Requires-Dist: threefive>=3.0.71
Requires-Dist: m3ufu>=0.0.97
Dynamic: author
Dynamic: author-email
Dynamic: classifier
Dynamic: description
Dynamic: description-content-type
Dynamic: home-page
Dynamic: license-file
Dynamic: platform
Dynamic: requires-dist
Dynamic: requires-python
Dynamic: summary
